demonproto/__init__.py
demonproto/e2ee.py
demonproto-9.9.dist-info/METADATA
demonproto-9.9.dist-info/WHEEL
demonproto-9.9.dist-info/top_level.txt
demonproto-9.9.dist-info/RECORD
